[
    {
        "date": "Sunday 15 April 2018",
        "fixtures": [
            {
                "home_team": "Newcastle",
                "away_team": "Arsenal",
                "score": "2-1",
                "url": "https://www.premierleague.com/match/22677",
                "details": {
                    "goals": [
                        {
                            "minute": "14",
                            "own_goal": "false",
                            "penalty": "false",
                            "scorer": "Alexandre Lacazette",
                            "assist": "Pierre-Emerick Aubameyang"
                        },
                        {
                            "minute": "29",
                            "own_goal": "false",
                            "penalty": "false",
                            "scorer": "Ayoze Pérez",
                            "assist": "DeAndre Yedlin"
                        },
                        {
                            "minute": "68",
                            "own_goal": "false",
                            "penalty": "false",
                            "scorer": "Matt Ritchie",
                            "assist": "Ayoze Pérez"
                        }
                    ],
                    "cards": [
                        {
                            "minute": "90",
                            "additional": "1",
                            "card": "yellow",
                            "player": "Islam Slimani"
                        }
                    ],
                    "substitutions": [
                        {
                            "minute": "63",
                            "in": "Islam Slimani",
                            "out": "Dwight Gayle"
                        },
                        {
                            "minute": "68",
                            "in": "Danny Welbeck",
                            "out": "Joe Willock"
                        },
                        {
                            "minute": "78",
                            "in": "Ainsley Maitland-Niles",
                            "out": "Calum Chambers"
                        },
                        {
                            "minute": "79",
                            "in": "Joselu",
                            "out": "Ayoze Pérez"
                        },
                        {
                            "minute": "86",
                            "in": "Jacob Murphy",
                            "out": "Matt Ritchie"
                        },
                        {
                            "minute": "86",
                            "in": "Eddie Nketiah",
                            "out": "Alex Iwobi"
                        }
                    ],
                    "referee": "Anthony Taylor",
                    "kick_off": "13:30"
                }
            },
            {
                "home_team": "Man Utd",
                "away_team": "West Brom",
                "score": "0-1",
                "url": "https://www.premierleague.com/match/22676",
                "details": {
                    "goals": [
                        {
                            "minute": "73",
                            "own_goal": "false",
                            "penalty": "false",
                            "scorer": "Jay Rodriguez"
                        }
                    ],
                    "cards": [
                        {
                            "minute": "29",
                            "card": "yellow",
                            "player": "Paul Pogba"
                        },
                        {
                            "minute": "77",
                            "card": "yellow",
                            "player": "Allan Nyom"
                        }
                    ],
                    "substitutions": [
                        {
                            "minute": "45",
                            "in": "Jesse Lingard",
                            "out": "Ander Herrera"
                        },
                        {
                            "minute": "58",
                            "in": "Anthony Martial",
                            "out": "Paul Pogba"
                        },
                        {
                            "minute": "75",
                            "in": "Marcus Rashford",
                            "out": "Ashley Young"
                        },
                        {
                            "minute": "77",
                            "in": "Grzegorz Krychowiak",
                            "out": "Matt Phillips"
                        },
                        {
                            "minute": "85",
                            "in": "Daniel Sturridge",
                            "out": "Salomón Rondón"
                        },
                        {
                            "minute": "90",
                            "additional": "4",
                            "in": "Claudio Yacob",
                            "out": "Chris Brunt"
                        }
                    ],
                    "referee": "Paul Tierney",
                    "kick_off": "16:00"
                }
            }
        ]
    }
]